[
  {
    "id": "6567a2515d2df017c44fee00",
    "type": "sell",
    "platinum": 16,
    "quantity": 1,
    "perTrade": 1,
    "visible": true,
    "createdAt": "2023-11-29T20:42:57Z",
    "updatedAt": "2026-06-23T22:49:25Z",
    "itemId": "5a9ed835b2b6a80133127c2f",
    "user": {
      "id": "60d233401970de0263fdb106",
      "ingameName": "CosmicProdigy",
      "slug": "cosmicprodigy",
      "avatar": "user/avatar/60d233401970de0263fdb106.png?8712bd8dd0299f637557f7755f0e1a8a",
      "reputation": 87,
      "platform": "pc",
      "crossplay": true,
      "locale": "en",
      "status": "offline",
      "activity": {
        "type": "UNKNOWN",
        "details": "unknown"
      },
      "lastSeen": "2026-06-30T05:57:20Z"
    }
  },
  {
    "id": "65c1bdc9fe113c038b6309fd",
    "type": "sell",
    "platinum": 120,
    "quantity": 2,
    "perTrade": 1,
    "visible": true,
    "createdAt": "2024-02-06T05:04:09Z",
    "updatedAt": "2024-02-06T05:04:09Z",
    "itemId": "5a9ed835b2b6a80133127c2f",
    "user": {
      "id": "6002e6664dd61401d5fdcb21",
      "ingameName": "-AoD-bazylkumpel",
      "slug": "aod-bazylkumpel",
      "avatar": "user/avatar/6002e6664dd61401d5fdcb21.png?8b7027373f60aaefda14fea754403255",
      "reputation": 1361,
      "platform": "pc",
      "crossplay": true,
      "locale": "en",
      "status": "offline",
      "activity": {
        "type": "UNKNOWN",
        "details": "unknown"
      },
      "lastSeen": "2026-06-30T17:42:18Z"
    }
  },
  {
    "id": "65c744d16d4fd10498834206",
    "type": "sell",
    "platinum": 18,
    "quantity": 1,
    "perTrade": 1,
    "visible": true,
    "createdAt": "2024-02-10T09:41:37Z",
    "updatedAt": "2026-05-17T16:34:50Z",
    "itemId": "5a9ed835b2b6a80133127c2f",
    "user": {
      "id": "61311c6abf2370018bfb3dfa",
      "ingameName": "Veerinn",
      "slug": "veerinn",
      "reputation": 7,
      "platform": "pc",
      "crossplay": true,
      "locale": "en",
      "status": "offline",
      "activity": {
        "type": "UNKNOWN",
        "details": "unknown"
      },
      "lastSeen": "2026-06-30T12:38:31Z"
    }
  },
  {
    "id": "65d49ee77fa45c000a60c90a",
    "type": "sell",
    "platinum": 20,
    "quantity": 6,
    "perTrade": 1,
    "visible": true,
    "createdAt": "2024-02-20T12:45:27Z",
    "updatedAt": "2026-06-23T12:49:02Z",
    "itemId": "5a9ed835b2b6a80133127c2f",
    "user": {
      "id": "651a49f2c9e4050121120fd9",
      "ingameName": "Dempt",
      "slug": "dempt",
      "reputation": 102,
      "platform": "pc",
      "crossplay": true,
      "locale": "zh-hans",
      "status": "offline",
      "activity": {
        "type": "UNKNOWN",
        "details": "unknown"
      },
      "lastSeen": "2026-06-30T03:51:51Z"
    }
  },
  {
    "id": "67218fb56b17412170d5c330",
    "type": "sell",
    "platinum": 20,
    "quantity": 1,
    "perTrade": 1,
    "visible": true,
    "createdAt": "2024-10-30T01:45:25Z",
    "updatedAt": "2026-06-30T20:04:01Z",
    "itemId": "5a9ed835b2b6a80133127c2f",
    "user": {
      "id": "64f819aa5fbd8100563f4d95",
      "ingameName": "pepa_cat",
      "slug": "pepa-cat",
      "reputation": 187,
      "platform": "pc",
      "crossplay": true,
      "locale": "en",
      "status": "offline",
      "activity": {
        "type": "UNKNOWN",
        "details": "unknown"
      },
      "lastSeen": "2026-06-30T21:43:47Z"
    }
  },
  {
    "id": "6732dc4463a2970181350eaa",
    "type": "sell",
    "platinum": 25,
    "quantity": 36,
    "perTrade": 1,
    "visible": true,
    "createdAt": "2024-11-12T04:40:36Z",
    "updatedAt": "2026-06-30T09:34:33Z",
    "itemId": "5a9ed835b2b6a80133127c2f",
    "user": {
      "id": "64cd86b68dfeea020b5a528d",
      "ingameName": "Xal.",
      "slug": "xal",
      "avatar": "user/avatar/64cd86b68dfeea020b5a528d.png?fc40b0f0a2b48b201972a23ef9cb7bf6",
      "reputation": 224,
      "platform": "pc",
      "crossplay": true,
      "locale": "en",
      "status": "offline",
      "activity": {
        "type": "UNKNOWN",
        "details": "unknown"
      },
      "lastSeen": "2026-06-30T21:32:57Z"
    }
  },
  {
    "id": "67a15734c1523905cfb2bd26",
    "type": "sell",
    "platinum": 80,
    "quantity": 1,
    "perTrade": 1,
    "visible": true,
    "createdAt": "2025-02-03T23:54:28Z",
    "updatedAt": "2025-02-03T23:54:28Z",
    "itemId": "5a9ed835b2b6a80133127c2f",
    "user": {
      "id": "654d99d52d2bbe08effab4e4",
      "ingameName": "ilyRogue",
      "slug": "ilyrogue",
      "avatar": "user/avatar/654d99d52d2bbe08effab4e4.png?96a6c8c4032a049ee955c6bf2b547424",
      "reputation": 593,
      "platform": "pc",
      "crossplay": true,
      "locale": "en",
      "status": "offline",
      "activity": {
        "type": "UNKNOWN",
        "details": "unknown"
      },
      "lastSeen": "2026-06-30T18:46:50Z"
    }
  },
  {
    "id": "67b04345093d4c08b9fb44e9",
    "type": "sell",
    "platinum": 25,
    "quantity": 7,
    "perTrade": 1,
    "visible": true,
    "createdAt": "2025-02-15T07:33:25Z",
    "updatedAt": "2026-06-08T08:22:33Z",
    "itemId": "5a9ed835b2b6a80133127c2f",
    "user": {
      "id": "64636bea3a1eb20b2f1ed57d",
      "ingameName": "x-hylo",
      "slug": "x-hylo",
      "avatar": "user/avatar/64636bea3a1eb20b2f1ed57d.png?dd43582e7bb4af053c4ee589ab8d9a32",
      "reputation": 49,
      "platform": "pc",
      "crossplay": true,
      "locale": "en",
      "status": "offline",
      "activity": {
        "type": "UNKNOWN",
        "details": "unknown"
      },
      "lastSeen": "2026-06-30T19:32:54Z"
    }
  },
  {
    "id": "67d4947142576700306330e6",
    "type": "sell",
    "platinum": 49,
    "quantity": 1,
    "perTrade": 1,
    "visible": true,
    "createdAt": "2025-03-14T20:41:21Z",
    "updatedAt": "2026-01-17T15:29:18Z",
    "itemId": "5a9ed835b2b6a80133127c2f",
    "user": {
      "id": "5c6b0e5d2cc6ce076191072c",
      "ingameName": "L-_-l...",
      "slug": "l-l-5832",
      "avatar": "user/avatar/5c6b0e5d2cc6ce076191072c.png?b6421e5e356ec71564e9f84d45e6692e",
      "reputation": 73,
      "platform": "pc",
      "crossplay": true,
      "locale": "en",
      "status": "offline",
      "activity": {
        "type": "UNKNOWN",
        "details": "unknown"
      },
      "lastSeen": "2026-06-29T20:12:35Z"
    }
  },
  {
    "id": "67eebdb519c10b0009182642",
    "type": "sell",
    "platinum": 19,
    "quantity": 1,
    "perTrade": 1,
    "visible": true,
    "createdAt": "2025-04-03T16:56:21Z",
    "updatedAt": "2026-06-26T22:14:49Z",
    "itemId": "5a9ed835b2b6a80133127c2f",
    "user": {
      "id": "5d715d2fab136c03729011d2",
      "ingameName": "Damjel",
      "slug": "damjel-0662",
      "avatar": "user/avatar/5d715d2fab136c03729011d2.png?1e0aa50987e9a8d1b17662d36f628d0a",
      "reputation": 75,
      "platform": "pc",
      "crossplay": true,
      "locale": "en",
      "status": "offline",
      "activity": {
        "type": "UNKNOWN",
        "details": "unknown"
      },
      "lastSeen": "2026-06-30T04:36:37Z"
    }
  },
  {
    "id": "67f16a50fde1ef002ce7e8a9",
    "type": "sell",
    "platinum": 19,
    "quantity": 1,
    "perTrade": 1,
    "visible": true,
    "createdAt": "2025-04-05T17:37:20Z",
    "updatedAt": "2026-06-27T15:47:21Z",
    "itemId": "5a9ed835b2b6a80133127c2f",
    "user": {
      "id": "67f03285fde1ef000a45b402",
      "ingameName": "404Karma",
      "slug": "404karma",
      "reputation": 10,
      "platform": "pc",
      "crossplay": true,
      "locale": "zh-hans",
      "status": "offline",
      "activity": {
        "type": "UNKNOWN",
        "details": "unknown"
      },
      "lastSeen": "2026-06-29T19:14:40Z"
    }
  },
  {
    "id": "6893e74e388ac8004fc84cc8",
    "type": "sell",
    "platinum": 40,
    "quantity": 5,
    "perTrade": 1,
    "visible": true,
    "createdAt": "2025-08-06T23:37:50Z",
    "updatedAt": "2026-04-13T00:38:18Z",
    "itemId": "5a9ed835b2b6a80133127c2f",
    "user": {
      "id": "5c0e925b7c90dc005d829172",
      "ingameName": "WitherAway17",
      "slug": "witheraway17",
      "avatar": "user/avatar/5c0e925b7c90dc005d829172.png?a12e3f73869de84f600807445f371f49",
      "reputation": 53,
      "platform": "pc",
      "crossplay": true,
      "locale": "en",
      "status": "ingame",
      "activity": {
        "type": "UNKNOWN",
        "details": "unknown"
      },
      "lastSeen": "2026-06-30T20:07:35Z"
    }
  },
  {
    "id": "6894760f44f5940024789215",
    "type": "sell",
    "platinum": 15,
    "quantity": 1,
    "perTrade": 1,
    "visible": true,
    "createdAt": "2025-08-07T09:46:55Z",
    "updatedAt": "2026-04-20T13:55:47Z",
    "itemId": "5a9ed835b2b6a80133127c2f",
    "user": {
      "id": "5b2fef19383eea062dbcb06d",
      "ingameName": "-_Fros7y_-",
      "slug": "fros7y",
      "reputation": 7,
      "platform": "pc",
      "crossplay": true,
      "locale": "ru",
      "status": "offline",
      "activity": {
        "type": "UNKNOWN",
        "details": "unknown"
      },
      "lastSeen": "2026-06-30T14:59:23Z"
    }
  },
  {
    "id": "68a1371a2a87dd00257b39a6",
    "type": "sell",
    "platinum": 20,
    "quantity": 1,
    "perTrade": 1,
    "visible": true,
    "createdAt": "2025-08-17T01:57:46Z",
    "updatedAt": "2026-06-21T20:27:41Z",
    "itemId": "5a9ed835b2b6a80133127c2f",
    "user": {
      "id": "67b1fa6028454f000ab41e5b",
      "ingameName": "PoiSwamm",
      "slug": "poiswamm",
      "reputation": 47,
      "platform": "pc",
      "crossplay": true,
      "locale": "zh-hans",
      "status": "offline",
      "activity": {
        "type": "UNKNOWN",
        "details": "unknown"
      },
      "lastSeen": "2026-06-29T01:03:40Z"
    }
  },
  {
    "id": "68bcce612a87dd001f40305a",
    "type": "sell",
    "platinum": 20,
    "quantity": 1,
    "perTrade": 1,
    "visible": true,
    "createdAt": "2025-09-07T00:14:25Z",
    "updatedAt": "2026-04-25T06:16:54Z",
    "itemId": "5a9ed835b2b6a80133127c2f",
    "user": {
      "id": "619b75a407cc9606b4526e47",
      "ingameName": "-Memento__Mori-",
      "slug": "memento-mori-1206",
      "reputation": 18,
      "platform": "pc",
      "crossplay": true,
      "locale": "ru",
      "status": "offline",
      "activity": {
        "type": "UNKNOWN",
        "details": "unknown"
      },
      "lastSeen": "2026-06-30T14:18:53Z"
    }
  },
  {
    "id": "68d476bcc2414c0037fc629e",
    "type": "sell",
    "platinum": 19,
    "quantity": 2,
    "perTrade": 1,
    "visible": true,
    "createdAt": "2025-09-24T22:54:52Z",
    "updatedAt": "2025-09-24T22:54:52Z",
    "itemId": "5a9ed835b2b6a80133127c2f",
    "user": {
      "id": "677d5913a77f1600077b5abb",
      "ingameName": "mollytov317",
      "slug": "mollytov317",
      "reputation": 20,
      "platform": "pc",
      "crossplay": true,
      "locale": "en",
      "status": "offline",
      "activity": {
        "type": "UNKNOWN",
        "details": "unknown"
      },
      "lastSeen": "2026-06-30T19:52:53Z"
    }
  },
  {
    "id": "68ffbaa81aa0427984f98274",
    "type": "sell",
    "platinum": 15,
    "quantity": 14,
    "perTrade": 1,
    "visible": true,
    "createdAt": "2025-10-27T18:32:08Z",
    "updatedAt": "2026-05-16T14:33:15Z",
    "itemId": "5a9ed835b2b6a80133127c2f",
    "user": {
      "id": "6798dd5d3ba9d803c1bf3ac3",
      "ingameName": "_SunBroPrime_",
      "slug": "sunbroprime",
      "reputation": 7,
      "platform": "pc",
      "crossplay": true,
      "locale": "ru",
      "status": "offline",
      "activity": {
        "type": "UNKNOWN",
        "details": "unknown"
      },
      "lastSeen": "2026-06-30T15:18:21Z"
    }
  },
  {
    "id": "6929cca945b966147e7b642c",
    "type": "sell",
    "platinum": 30,
    "quantity": 1,
    "perTrade": 1,
    "visible": true,
    "createdAt": "2025-11-28T16:24:09Z",
    "updatedAt": "2025-11-28T16:24:09Z",
    "itemId": "5a9ed835b2b6a80133127c2f",
    "user": {
      "id": "6826eafc0193350007cb7fc1",
      "ingameName": "LordPortoo",
      "slug": "lordportoo",
      "reputation": 16,
      "platform": "pc",
      "crossplay": true,
      "locale": "en",
      "status": "offline",
      "activity": {
        "type": "UNKNOWN",
        "details": "unknown"
      },
      "lastSeen": "2026-06-30T19:41:21Z"
    }
  },
  {
    "id": "69385d3be5c94bc272e17a00",
    "type": "sell",
    "platinum": 30,
    "quantity": 1,
    "perTrade": 1,
    "visible": true,
    "createdAt": "2025-12-09T17:32:43Z",
    "updatedAt": "2025-12-09T17:33:02Z",
    "itemId": "5a9ed835b2b6a80133127c2f",
    "user": {
      "id": "65e8b30ec2e648000a9d1af6",
      "ingameName": "Isler98",
      "slug": "isler98",
      "reputation": 8,
      "platform": "pc",
      "crossplay": true,
      "locale": "es",
      "status": "online",
      "activity": {
        "type": "UNKNOWN",
        "details": "unknown"
      },
      "lastSeen": "2026-06-30T21:20:57Z"
    }
  },
  {
    "id": "6938db00e5c94bc272e20486",
    "type": "sell",
    "platinum": 13,
    "quantity": 1,
    "perTrade": 1,
    "visible": true,
    "createdAt": "2025-12-10T02:29:20Z",
    "updatedAt": "2026-01-29T00:29:09Z",
    "itemId": "5a9ed835b2b6a80133127c2f",
    "user": {
      "id": "690173eeb06cb80007a0fed8",
      "ingameName": "MD_Gelelli",
      "slug": "md_gelelli",
      "reputation": 3,
      "platform": "pc",
      "crossplay": true,
      "locale": "es",
      "status": "offline",
      "activity": {
        "type": "UNKNOWN",
        "details": "unknown"
      },
      "lastSeen": "2026-06-30T03:55:27Z"
    }
  },
  {
    "id": "693eface6370c5725c80a8a9",
    "type": "sell",
    "platinum": 15,
    "quantity": 1,
    "perTrade": 1,
    "visible": true,
    "createdAt": "2025-12-14T17:58:38Z",
    "updatedAt": "2026-03-26T09:43:17Z",
    "itemId": "5a9ed835b2b6a80133127c2f",
    "user": {
      "id": "58bc0231d3ffb647bf895073",
      "ingameName": "Darkjeminai",
      "slug": "darkjeminai",
      "reputation": 19,
      "platform": "pc",
      "crossplay": true,
      "locale": "en",
      "status": "offline",
      "activity": {
        "type": "UNKNOWN",
        "details": "unknown"
      },
      "lastSeen": "2026-06-30T11:05:58Z"
    }
  },
  {
    "id": "696d4749a7a2008a73816439",
    "type": "sell",
    "platinum": 10,
    "quantity": 1,
    "perTrade": 1,
    "visible": true,
    "createdAt": "2026-01-18T20:49:13Z",
    "updatedAt": "2026-06-23T04:29:27Z",
    "itemId": "5a9ed835b2b6a80133127c2f",
    "user": {
      "id": "68e7d1dca0f9e4000bc82e39",
      "ingameName": "ElmapachitoGabi",
      "slug": "elmapachitogabi",
      "reputation": 1,
      "platform": "pc",
      "crossplay": true,
      "locale": "en",
      "status": "offline",
      "activity": {
        "type": "UNKNOWN",
        "details": "unknown"
      },
      "lastSeen": "2026-06-30T20:10:35Z"
    }
  },
  {
    "id": "699641386a51e1b3b005129d",
    "type": "sell",
    "platinum": 20,
    "quantity": 1,
    "perTrade": 1,
    "visible": true,
    "createdAt": "2026-02-18T22:46:16Z",
    "updatedAt": "2026-02-18T22:46:16Z",
    "itemId": "5a9ed835b2b6a80133127c2f",
    "user": {
      "id": "694491a31deed4003d7232a6",
      "ingameName": "lufeilufei",
      "slug": "lufeilufei",
      "reputation": 6,
      "platform": "pc",
      "crossplay": true,
      "locale": "zh-hans",
      "status": "offline",
      "activity": {
        "type": "UNKNOWN",
        "details": "unknown"
      },
      "lastSeen": "2026-06-30T18:47:16Z"
    }
  },
  {
    "id": "6997375fa7a2008a73beab5a",
    "type": "sell",
    "platinum": 20,
    "quantity": 2,
    "perTrade": 1,
    "visible": true,
    "createdAt": "2026-02-19T16:16:31Z",
    "updatedAt": "2026-06-24T13:42:33Z",
    "itemId": "5a9ed835b2b6a80133127c2f",
    "user": {
      "id": "63a459378f2b27090891e2d9",
      "ingameName": "DonLeonard",
      "slug": "donleonard",
      "avatar": "user/avatar/63a459378f2b27090891e2d9.png?14dfcd25aea127a64e58f00352f39f61",
      "reputation": 18,
      "platform": "pc",
      "crossplay": true,
      "locale": "ru",
      "status": "offline",
      "activity": {
        "type": "UNKNOWN",
        "details": "unknown"
      },
      "lastSeen": "2026-06-30T21:05:14Z"
    }
  },
  {
    "id": "699b1d35a7a2008a73c47f27",
    "type": "sell",
    "platinum": 20,
    "quantity": 1,
    "perTrade": 1,
    "visible": true,
    "createdAt": "2026-02-22T15:13:57Z",
    "updatedAt": "2026-05-04T14:43:59Z",
    "itemId": "5a9ed835b2b6a80133127c2f",
    "user": {
      "id": "6934751426c18b00494a9235",
      "ingameName": "CraiNCaesar",
      "slug": "craincaesar",
      "avatar": "user/avatar/6934751426c18b00494a9235.9dc120d6.webp",
      "reputation": 24,
      "platform": "pc",
      "crossplay": true,
      "locale": "en",
      "status": "offline",
      "activity": {
        "type": "UNKNOWN",
        "details": "unknown"
      },
      "lastSeen": "2026-06-30T16:47:46Z"
    }
  },
  {
    "id": "699e24ff6a51e1b3b010b132",
    "type": "sell",
    "platinum": 20,
    "quantity": 4,
    "perTrade": 1,
    "visible": true,
    "createdAt": "2026-02-24T22:23:59Z",
    "updatedAt": "2026-06-11T03:55:55Z",
    "itemId": "5a9ed835b2b6a80133127c2f",
    "user": {
      "id": "68a20538ed793900097254d6",
      "ingameName": "ShyDoggy",
      "slug": "shydoggy",
      "reputation": 41,
      "platform": "pc",
      "crossplay": true,
      "locale": "en",
      "status": "offline",
      "activity": {
        "type": "UNKNOWN",
        "details": "unknown"
      },
      "lastSeen": "2026-06-30T20:23:33Z"
    }
  },
  {
    "id": "69ad939d6a51e1b3b0240bb2",
    "type": "sell",
    "platinum": 65,
    "quantity": 1,
    "perTrade": 1,
    "visible": true,
    "createdAt": "2026-03-08T15:19:57Z",
    "updatedAt": "2026-03-08T15:19:57Z",
    "itemId": "5a9ed835b2b6a80133127c2f",
    "user": {
      "id": "5b49294e9c030900b415f61b",
      "ingameName": "xYIZAx",
      "slug": "xyizax",
      "avatar": "user/avatar/5b49294e9c030900b415f61b.png?605759fdf929f385da8e3d93ef1f56f4",
      "reputation": 1,
      "platform": "pc",
      "crossplay": true,
      "locale": "en",
      "status": "offline",
      "activity": {
        "type": "UNKNOWN",
        "details": "unknown"
      },
      "lastSeen": "2026-06-30T20:51:10Z"
    }
  },
  {
    "id": "69b4ae306a51e1b3b02c1736",
    "type": "sell",
    "platinum": 30,
    "quantity": 11,
    "perTrade": 1,
    "visible": true,
    "createdAt": "2026-03-14T00:39:12Z",
    "updatedAt": "2026-05-30T02:53:40Z",
    "itemId": "5a9ed835b2b6a80133127c2f",
    "user": {
      "id": "679f02eb603c79000831f9f9",
      "ingameName": "Theoriit",
      "slug": "theoriit",
      "reputation": 12,
      "platform": "pc",
      "crossplay": true,
      "locale": "en",
      "status": "offline",
      "activity": {
        "type": "UNKNOWN",
        "details": "unknown"
      },
      "lastSeen": "2026-06-30T15:27:18Z"
    }
  },
  {
    "id": "69bc17f321d9214b27a95a40",
    "type": "sell",
    "platinum": 20,
    "quantity": 1,
    "perTrade": 1,
    "visible": true,
    "createdAt": "2026-03-19T15:36:19Z",
    "updatedAt": "2026-05-25T11:24:54Z",
    "itemId": "5a9ed835b2b6a80133127c2f",
    "user": {
      "id": "5fa944bf92757c02a227913f",
      "ingameName": "SupremeMister",
      "slug": "suprememister",
      "avatar": "user/avatar/5fa944bf92757c02a227913f.c729397f.webp",
      "reputation": 13,
      "platform": "pc",
      "crossplay": true,
      "locale": "en",
      "status": "offline",
      "activity": {
        "type": "UNKNOWN",
        "details": "unknown"
      },
      "lastSeen": "2026-06-30T19:09:04Z"
    }
  },
  {
    "id": "69c49df96dcee099e12d3feb",
    "type": "sell",
    "platinum": 10,
    "quantity": 3,
    "perTrade": 1,
    "visible": true,
    "createdAt": "2026-03-26T02:46:17Z",
    "updatedAt": "2026-03-26T15:25:34Z",
    "itemId": "5a9ed835b2b6a80133127c2f",
    "user": {
      "id": "664847015ca32210456121e0",
      "ingameName": "R.E.R.I.S.E",
      "slug": "r-e-r-i-s-e",
      "reputation": 7,
      "platform": "pc",
      "crossplay": true,
      "locale": "zh-hans",
      "status": "offline",
      "activity": {
        "type": "UNKNOWN",
        "details": "unknown"
      },
      "lastSeen": "2026-06-29T08:11:39Z"
    }
  },
  {
    "id": "69cea403795a0d8e54b8b741",
    "type": "sell",
    "platinum": 20,
    "quantity": 1,
    "perTrade": 1,
    "visible": true,
    "createdAt": "2026-04-02T17:14:43Z",
    "updatedAt": "2026-05-30T21:29:13Z",
    "itemId": "5a9ed835b2b6a80133127c2f",
    "user": {
      "id": "67ed084022797f00079986c4",
      "ingameName": "xotriks",
      "slug": "xotriks",
      "avatar": "user/avatar/67ed084022797f00079986c4.png?60e5bd42f815546d6e6d8a2adc946d51",
      "reputation": 9,
      "platform": "pc",
      "crossplay": true,
      "locale": "en",
      "status": "offline",
      "activity": {
        "type": "UNKNOWN",
        "details": "unknown"
      },
      "lastSeen": "2026-06-30T20:45:00Z"
    }
  },
  {
    "id": "69df31c81327c7310cc0b0d8",
    "type": "sell",
    "platinum": 180,
    "quantity": 1,
    "perTrade": 1,
    "visible": true,
    "createdAt": "2026-04-15T06:35:52Z",
    "updatedAt": "2026-04-15T06:35:52Z",
    "itemId": "5a9ed835b2b6a80133127c2f",
    "user": {
      "id": "6824bf45fde1ef0427e442e1",
      "ingameName": "Lys_Of_Damned",
      "slug": "lys_of_damned",
      "avatar": "user/avatar/6824bf45fde1ef0427e442e1.da4f2666.webp",
      "reputation": 90,
      "platform": "pc",
      "crossplay": true,
      "locale": "en",
      "status": "ingame",
      "activity": {
        "type": "UNKNOWN",
        "details": "unknown"
      },
      "lastSeen": "2026-06-30T18:46:11Z"
    }
  },
  {
    "id": "69e01cbf1327c7310cc2299f",
    "type": "sell",
    "platinum": 80,
    "quantity": 1,
    "perTrade": 1,
    "visible": true,
    "createdAt": "2026-04-15T23:18:23Z",
    "updatedAt": "2026-04-15T23:18:23Z",
    "itemId": "5a9ed835b2b6a80133127c2f",
    "user": {
      "id": "60808698e168df00f1aef6d2",
      "ingameName": "-AoD-Eronix",
      "slug": "aod-eronix",
      "avatar": "user/avatar/60808698e168df00f1aef6d2.png?8cc95a93468ee85258c1ba5c5dad1ea8",
      "reputation": 143,
      "platform": "pc",
      "crossplay": true,
      "locale": "en",
      "status": "offline",
      "activity": {
        "type": "UNKNOWN",
        "details": "unknown"
      },
      "lastSeen": "2026-06-30T17:34:43Z"
    }
  },
  {
    "id": "69e353e0bde90925afc9147e",
    "type": "sell",
    "platinum": 66,
    "quantity": 1,
    "perTrade": 1,
    "visible": true,
    "createdAt": "2026-04-18T09:50:24Z",
    "updatedAt": "2026-05-22T08:22:15Z",
    "itemId": "5a9ed835b2b6a80133127c2f",
    "user": {
      "id": "69d734b17a062e0075ae6fdf",
      "ingameName": "jackiemaxx",
      "slug": "jackiemaxx",
      "reputation": 1,
      "platform": "pc",
      "crossplay": true,
      "locale": "zh-hans",
      "status": "offline",
      "activity": {
        "type": "UNKNOWN",
        "details": "unknown"
      },
      "lastSeen": "2026-06-29T11:39:27Z"
    }
  },
  {
    "id": "69ec8b24a2ed6afbb64b762b",
    "type": "sell",
    "platinum": 20,
    "quantity": 2,
    "perTrade": 1,
    "visible": true,
    "createdAt": "2026-04-25T09:36:36Z",
    "updatedAt": "2026-06-28T15:26:23Z",
    "itemId": "5a9ed835b2b6a80133127c2f",
    "user": {
      "id": "6281ef1cf2b88801a5377ea0",
      "ingameName": "GaGaRuYN",
      "slug": "gagaruyn",
      "reputation": 2,
      "platform": "pc",
      "crossplay": true,
      "locale": "ru",
      "status": "offline",
      "activity": {
        "type": "UNKNOWN",
        "details": "unknown"
      },
      "lastSeen": "2026-06-29T16:26:06Z"
    }
  },
  {
    "id": "69efaa81a2ed6afbb6503477",
    "type": "sell",
    "platinum": 18,
    "quantity": 3,
    "perTrade": 1,
    "visible": true,
    "createdAt": "2026-04-27T18:27:13Z",
    "updatedAt": "2026-04-27T18:27:13Z",
    "itemId": "5a9ed835b2b6a80133127c2f",
    "user": {
      "id": "65b58904fe113c00c1074556",
      "ingameName": "_flamey18",
      "slug": "flamey18",
      "avatar": "user/avatar/65b58904fe113c00c1074556.57ab1587.webp",
      "reputation": 77,
      "platform": "pc",
      "crossplay": true,
      "locale": "en",
      "status": "offline",
      "activity": {
        "type": "UNKNOWN",
        "details": "unknown"
      },
      "lastSeen": "2026-06-30T21:06:35Z"
    }
  },
  {
    "id": "69f45214c4f5385570c50da3",
    "type": "sell",
    "platinum": 20,
    "quantity": 1,
    "perTrade": 1,
    "visible": true,
    "createdAt": "2026-05-01T07:11:16Z",
    "updatedAt": "2026-05-01T07:11:16Z",
    "itemId": "5a9ed835b2b6a80133127c2f",
    "user": {
      "id": "60592f9006ec65006959ad1a",
      "ingameName": "LordOfDeer",
      "slug": "lordofdeer",
      "avatar": "user/avatar/60592f9006ec65006959ad1a.59fdb074.webp",
      "reputation": 23,
      "platform": "pc",
      "crossplay": true,
      "locale": "en",
      "status": "offline",
      "activity": {
        "type": "UNKNOWN",
        "details": "unknown"
      },
      "lastSeen": "2026-06-30T21:36:09Z"
    }
  },
  {
    "id": "69f4cd21c4f5385570c5c7a7",
    "type": "sell",
    "platinum": 39,
    "quantity": 1,
    "perTrade": 1,
    "visible": true,
    "createdAt": "2026-05-01T15:56:17Z",
    "updatedAt": "2026-06-25T11:12:28Z",
    "itemId": "5a9ed835b2b6a80133127c2f",
    "user": {
      "id": "62c1b2aaf26d880b83a4e388",
      "ingameName": "raku1337",
      "slug": "raku1337",
      "reputation": 15,
      "platform": "pc",
      "crossplay": true,
      "locale": "en",
      "status": "offline",
      "activity": {
        "type": "UNKNOWN",
        "details": "unknown"
      },
      "lastSeen": "2026-06-30T11:11:57Z"
    }
  },
  {
    "id": "6a0586cac4f5385570dbe352",
    "type": "sell",
    "platinum": 29,
    "quantity": 1,
    "perTrade": 1,
    "visible": true,
    "createdAt": "2026-05-14T08:24:42Z",
    "updatedAt": "2026-05-31T08:11:01Z",
    "itemId": "5a9ed835b2b6a80133127c2f",
    "user": {
      "id": "67e9d5863b988a0009c34422",
      "ingameName": "Kodry",
      "slug": "kodry",
      "reputation": 2,
      "platform": "pc",
      "crossplay": true,
      "locale": "en",
      "status": "offline",
      "activity": {
        "type": "UNKNOWN",
        "details": "unknown"
      },
      "lastSeen": "2026-06-30T05:36:22Z"
    }
  },
  {
    "id": "6a0aad0dc4f5385570e316e3",
    "type": "sell",
    "platinum": 17,
    "quantity": 2,
    "perTrade": 1,
    "visible": true,
    "createdAt": "2026-05-18T06:09:17Z",
    "updatedAt": "2026-05-18T06:09:17Z",
    "itemId": "5a9ed835b2b6a80133127c2f",
    "user": {
      "id": "67fa75ed8e487d000b99580f",
      "ingameName": "Rainych_doro",
      "slug": "rainych_doro",
      "avatar": "user/avatar/67fa75ed8e487d000b99580f.7a7c1ba2.webp",
      "reputation": 8,
      "platform": "pc",
      "crossplay": true,
      "locale": "zh-hans",
      "status": "offline",
      "activity": {
        "type": "UNKNOWN",
        "details": "unknown"
      },
      "lastSeen": "2026-06-29T12:43:54Z"
    }
  },
  {
    "id": "6a0e2dcfa2ed6afbb6772c51",
    "type": "sell",
    "platinum": 30,
    "quantity": 1,
    "perTrade": 1,
    "visible": true,
    "createdAt": "2026-05-20T21:55:27Z",
    "updatedAt": "2026-06-30T20:06:05Z",
    "itemId": "5a9ed835b2b6a80133127c2f",
    "user": {
      "id": "5c74b248e12a2d07b41b87b4",
      "ingameName": "KimeraUchuu",
      "slug": "kimerauchuu",
      "reputation": 8,
      "platform": "pc",
      "crossplay": true,
      "locale": "en",
      "status": "offline",
      "activity": {
        "type": "UNKNOWN",
        "details": "unknown"
      },
      "lastSeen": "2026-06-30T20:38:49Z"
    }
  },
  {
    "id": "6a17d5eac4f5385570f2efde",
    "type": "sell",
    "platinum": 20,
    "quantity": 3,
    "perTrade": 1,
    "visible": true,
    "createdAt": "2026-05-28T05:43:06Z",
    "updatedAt": "2026-05-28T05:43:06Z",
    "itemId": "5a9ed835b2b6a80133127c2f",
    "user": {
      "id": "69f98a8b6e47700241fc81fc",
      "ingameName": "ianlie123",
      "slug": "ianlie123",
      "reputation": 5,
      "platform": "pc",
      "crossplay": true,
      "locale": "zh-hans",
      "status": "offline",
      "activity": {
        "type": "UNKNOWN",
        "details": "unknown"
      },
      "lastSeen": "2026-06-29T01:32:45Z"
    }
  },
  {
    "id": "6a198c6ff43d99f711fbf09a",
    "type": "sell",
    "platinum": 50,
    "quantity": 1,
    "perTrade": 1,
    "visible": true,
    "createdAt": "2026-05-29T12:54:07Z",
    "updatedAt": "2026-05-29T12:54:07Z",
    "itemId": "5a9ed835b2b6a80133127c2f",
    "user": {
      "id": "698fe6ab5734ba07b12274cc",
      "ingameName": "Vishu130789",
      "slug": "vishu130789",
      "reputation": 4,
      "platform": "pc",
      "crossplay": true,
      "locale": "en",
      "status": "offline",
      "activity": {
        "type": "UNKNOWN",
        "details": "unknown"
      },
      "lastSeen": "2026-06-30T17:20:40Z"
    }
  },
  {
    "id": "6a1afe6990a8bc914c072b86",
    "type": "sell",
    "platinum": 20,
    "quantity": 12,
    "perTrade": 1,
    "visible": true,
    "createdAt": "2026-05-30T15:12:41Z",
    "updatedAt": "2026-06-07T14:06:19Z",
    "itemId": "5a9ed835b2b6a80133127c2f",
    "user": {
      "id": "6946c6b4d65c7b006764b46c",
      "ingameName": "MujicaMortis",
      "slug": "mujicamortis",
      "reputation": 117,
      "platform": "pc",
      "crossplay": true,
      "locale": "en",
      "status": "offline",
      "activity": {
        "type": "UNKNOWN",
        "details": "unknown"
      },
      "lastSeen": "2026-06-30T15:07:11Z"
    }
  },
  {
    "id": "6a1d6b3d90a8bc914c0a3a3b",
    "type": "sell",
    "platinum": 20,
    "quantity": 1,
    "perTrade": 1,
    "visible": true,
    "createdAt": "2026-06-01T11:21:33Z",
    "updatedAt": "2026-06-21T12:51:59Z",
    "itemId": "5a9ed835b2b6a80133127c2f",
    "user": {
      "id": "6548c90a5d2df0052252a852",
      "ingameName": "Zoner234",
      "slug": "zoner234",
      "reputation": 7,
      "platform": "pc",
      "crossplay": true,
      "locale": "ru",
      "status": "offline",
      "activity": {
        "type": "UNKNOWN",
        "details": "unknown"
      },
      "lastSeen": "2026-06-30T17:53:09Z"
    }
  },
  {
    "id": "6a2284c890a8bc914c102b9b",
    "type": "buy",
    "platinum": 10,
    "quantity": 15,
    "perTrade": 1,
    "visible": true,
    "createdAt": "2026-06-05T08:11:52Z",
    "updatedAt": "2026-06-10T20:01:47Z",
    "itemId": "5a9ed835b2b6a80133127c2f",
    "user": {
      "id": "65d213108d163f00094beeee",
      "ingameName": "C3Sovereignty",
      "slug": "c3sovereignty",
      "avatar": "user/avatar/65d213108d163f00094beeee.fe79a603.webp",
      "reputation": 130,
      "platform": "pc",
      "crossplay": true,
      "locale": "en",
      "status": "offline",
      "activity": {
        "type": "UNKNOWN",
        "details": "unknown"
      },
      "lastSeen": "2026-06-30T21:19:33Z"
    }
  },
  {
    "id": "6a26d694f43d99f7110bba3e",
    "type": "sell",
    "platinum": 20,
    "quantity": 5,
    "perTrade": 1,
    "visible": true,
    "createdAt": "2026-06-08T14:49:56Z",
    "updatedAt": "2026-06-13T13:57:45Z",
    "itemId": "5a9ed835b2b6a80133127c2f",
    "user": {
      "id": "6856d6fadb2d75004ede7232",
      "ingameName": "GrahamMayhem",
      "slug": "grahammayhem",
      "avatar": "user/avatar/6856d6fadb2d75004ede7232.2b2c6e7a.webp",
      "reputation": 54,
      "platform": "pc",
      "crossplay": true,
      "locale": "en",
      "status": "offline",
      "activity": {
        "type": "UNKNOWN",
        "details": "unknown"
      },
      "lastSeen": "2026-06-30T20:50:50Z"
    }
  },
  {
    "id": "6a274626f43d99f7110c46d2",
    "type": "sell",
    "platinum": 24,
    "quantity": 1,
    "perTrade": 1,
    "visible": true,
    "createdAt": "2026-06-08T22:45:58Z",
    "updatedAt": "2026-06-08T22:45:58Z",
    "itemId": "5a9ed835b2b6a80133127c2f",
    "user": {
      "id": "69ea1f9cf8d0110043506d3c",
      "ingameName": "Cameron4331",
      "slug": "cameron4331",
      "reputation": 8,
      "platform": "pc",
      "crossplay": true,
      "locale": "en",
      "status": "offline",
      "activity": {
        "type": "UNKNOWN",
        "details": "unknown"
      },
      "lastSeen": "2026-06-30T13:12:45Z"
    }
  },
  {
    "id": "6a289fadf43d99f7110db286",
    "type": "buy",
    "platinum": 15,
    "quantity": 1,
    "perTrade": 1,
    "visible": true,
    "createdAt": "2026-06-09T23:20:13Z",
    "updatedAt": "2026-06-09T23:20:13Z",
    "itemId": "5a9ed835b2b6a80133127c2f",
    "user": {
      "id": "69dd5dcd34493d01a14d7357",
      "ingameName": "Ducky0001",
      "slug": "ducky0001",
      "avatar": "user/avatar/69dd5dcd34493d01a14d7357.4aeac147.webp",
      "reputation": 8,
      "platform": "pc",
      "crossplay": true,
      "locale": "en",
      "status": "offline",
      "activity": {
        "type": "UNKNOWN",
        "details": "unknown"
      },
      "lastSeen": "2026-06-30T21:33:11Z"
    }
  },
  {
    "id": "6a2983a890a8bc914c1856a3",
    "type": "sell",
    "platinum": 20,
    "quantity": 1,
    "perTrade": 1,
    "visible": true,
    "createdAt": "2026-06-10T15:32:56Z",
    "updatedAt": "2026-06-27T15:49:53Z",
    "itemId": "5a9ed835b2b6a80133127c2f",
    "user": {
      "id": "67f03285fde1ef000a45b402",
      "ingameName": "404Karma",
      "slug": "404karma",
      "reputation": 10,
      "platform": "pc",
      "crossplay": true,
      "locale": "zh-hans",
      "status": "offline",
      "activity": {
        "type": "UNKNOWN",
        "details": "unknown"
      },
      "lastSeen": "2026-06-29T19:14:40Z"
    }
  },
  {
    "id": "6a2a035390a8bc914c18f376",
    "type": "sell",
    "platinum": 25,
    "quantity": 1,
    "perTrade": 1,
    "visible": true,
    "createdAt": "2026-06-11T00:37:39Z",
    "updatedAt": "2026-06-11T00:37:39Z",
    "itemId": "5a9ed835b2b6a80133127c2f",
    "user": {
      "id": "5af52f20b0a6a403f8fa383d",
      "ingameName": "KoSKillshot",
      "slug": "koskillshot",
      "reputation": 22,
      "platform": "pc",
      "crossplay": true,
      "locale": "en",
      "status": "offline",
      "activity": {
        "type": "UNKNOWN",
        "details": "unknown"
      },
      "lastSeen": "2026-06-30T03:09:43Z"
    }
  },
  {
    "id": "6a2a29c690a8bc914c191d1a",
    "type": "sell",
    "platinum": 40,
    "quantity": 1,
    "perTrade": 1,
    "visible": true,
    "createdAt": "2026-06-11T03:21:42Z",
    "updatedAt": "2026-06-11T03:21:42Z",
    "itemId": "5a9ed835b2b6a80133127c2f",
    "user": {
      "id": "5d0ed9cf6e65e803d0bdec57",
      "ingameName": "TzKal_Majora",
      "slug": "tzkal_majora",
      "reputation": 2,
      "platform": "pc",
      "crossplay": true,
      "locale": "en",
      "status": "offline",
      "activity": {
        "type": "UNKNOWN",
        "details": "unknown"
      },
      "lastSeen": "2026-06-30T20:07:45Z"
    }
  },
  {
    "id": "6a2da6ebd914e16b557b7cba",
    "type": "sell",
    "platinum": 19,
    "quantity": 1,
    "perTrade": 1,
    "visible": true,
    "createdAt": "2026-06-13T18:52:27Z",
    "updatedAt": "2026-06-13T18:52:37Z",
    "itemId": "5a9ed835b2b6a80133127c2f",
    "user": {
      "id": "5ecc27377d0c9a06f37c7edb",
      "ingameName": "Touchette",
      "slug": "touchette",
      "avatar": "user/avatar/5ecc27377d0c9a06f37c7edb.png?5e0a46768d5ce54b899b8c3604e946ea",
      "reputation": 25,
      "platform": "pc",
      "crossplay": true,
      "locale": "en",
      "status": "offline",
      "activity": {
        "type": "UNKNOWN",
        "details": "unknown"
      },
      "lastSeen": "2026-06-30T16:24:57Z"
    }
  },
  {
    "id": "6a367c3c101d503e3d58ee45",
    "type": "buy",
    "platinum": 5,
    "quantity": 6,
    "perTrade": 1,
    "visible": true,
    "createdAt": "2026-06-20T11:40:44Z",
    "updatedAt": "2026-06-23T10:45:16Z",
    "itemId": "5a9ed835b2b6a80133127c2f",
    "user": {
      "id": "64f01166b74901060c9ebe19",
      "ingameName": "EruRapapa",
      "slug": "erurapapa",
      "reputation": 32,
      "platform": "pc",
      "crossplay": true,
      "locale": "zh-hans",
      "status": "offline",
      "activity": {
        "type": "UNKNOWN",
        "details": "unknown"
      },
      "lastSeen": "2026-06-30T16:08:02Z"
    }
  },
  {
    "id": "6a36b248d914e16b55868ec5",
    "type": "sell",
    "platinum": 19,
    "quantity": 1,
    "perTrade": 1,
    "visible": true,
    "createdAt": "2026-06-20T15:31:20Z",
    "updatedAt": "2026-06-20T15:31:20Z",
    "itemId": "5a9ed835b2b6a80133127c2f",
    "user": {
      "id": "6a281592580ed50255483d48",
      "ingameName": "KayncerGaming",
      "slug": "kayncergaming",
      "reputation": 0,
      "platform": "pc",
      "crossplay": true,
      "locale": "en",
      "status": "offline",
      "activity": {
        "type": "UNKNOWN",
        "details": "unknown"
      },
      "lastSeen": "2026-06-30T08:07:41Z"
    }
  },
  {
    "id": "6a375aa6101d503e3d5a4676",
    "type": "sell",
    "platinum": 22,
    "quantity": 1,
    "perTrade": 1,
    "visible": true,
    "createdAt": "2026-06-21T03:29:42Z",
    "updatedAt": "2026-06-28T09:07:54Z",
    "itemId": "5a9ed835b2b6a80133127c2f",
    "user": {
      "id": "6185ceb44c545b03c46b1cfa",
      "ingameName": "Bagguett",
      "slug": "bagguett",
      "reputation": 24,
      "platform": "pc",
      "crossplay": true,
      "locale": "en",
      "status": "offline",
      "activity": {
        "type": "UNKNOWN",
        "details": "unknown"
      },
      "lastSeen": "2026-06-30T09:58:25Z"
    }
  },
  {
    "id": "6a3969fe86fc399ad4a0c3be",
    "type": "sell",
    "platinum": 20,
    "quantity": 1,
    "perTrade": 1,
    "visible": true,
    "createdAt": "2026-06-22T16:59:42Z",
    "updatedAt": "2026-06-29T16:54:53Z",
    "itemId": "5a9ed835b2b6a80133127c2f",
    "user": {
      "id": "694a76fcf57fc90008c54675",
      "ingameName": "DeriannaPrime",
      "slug": "deriannaprime",
      "reputation": 10,
      "platform": "pc",
      "crossplay": true,
      "locale": "ru",
      "status": "offline",
      "activity": {
        "type": "UNKNOWN",
        "details": "unknown"
      },
      "lastSeen": "2026-06-30T12:38:33Z"
    }
  },
  {
    "id": "6a3a6f392202c9dc0ac51617",
    "type": "sell",
    "platinum": 15,
    "quantity": 1,
    "perTrade": 1,
    "visible": true,
    "createdAt": "2026-06-23T11:34:17Z",
    "updatedAt": "2026-06-23T11:34:17Z",
    "itemId": "5a9ed835b2b6a80133127c2f",
    "user": {
      "id": "5e367eb119599200342f1e7c",
      "ingameName": "Byczek1980",
      "slug": "byczek1980",
      "reputation": 42,
      "platform": "pc",
      "crossplay": true,
      "locale": "en",
      "status": "offline",
      "activity": {
        "type": "UNKNOWN",
        "details": "unknown"
      },
      "lastSeen": "2026-06-29T08:08:38Z"
    }
  },
  {
    "id": "6a3d706686fc399ad4a620ff",
    "type": "sell",
    "platinum": 25,
    "quantity": 1,
    "perTrade": 1,
    "visible": true,
    "createdAt": "2026-06-25T18:16:06Z",
    "updatedAt": "2026-06-25T18:16:06Z",
    "itemId": "5a9ed835b2b6a80133127c2f",
    "user": {
      "id": "6a163f07dcc12301b04fef2e",
      "ingameName": "andrezz21",
      "slug": "andrezz21",
      "reputation": 3,
      "platform": "pc",
      "crossplay": true,
      "locale": "es",
      "status": "offline",
      "activity": {
        "type": "UNKNOWN",
        "details": "unknown"
      },
      "lastSeen": "2026-06-29T19:51:04Z"
    }
  },
  {
    "id": "6a3da7d22202c9dc0ac990c3",
    "type": "buy",
    "platinum": 10,
    "quantity": 6,
    "perTrade": 1,
    "visible": true,
    "createdAt": "2026-06-25T22:12:34Z",
    "updatedAt": "2026-06-30T20:49:08Z",
    "itemId": "5a9ed835b2b6a80133127c2f",
    "user": {
      "id": "589df696d3ffb6078ad98410",
      "ingameName": "ImbaSword",
      "slug": "imbasword",
      "avatar": "user/avatar/589df696d3ffb6078ad98410.png?b60df8c5ba8d4310de1957469d24d148",
      "reputation": 12,
      "platform": "pc",
      "crossplay": true,
      "locale": "en",
      "status": "offline",
      "activity": {
        "type": "UNKNOWN",
        "details": "unknown"
      },
      "lastSeen": "2026-06-30T21:06:17Z"
    }
  },
  {
    "id": "6a3ea81f86fc399ad4a7ae8d",
    "type": "sell",
    "platinum": 20,
    "quantity": 3,
    "perTrade": 1,
    "visible": true,
    "createdAt": "2026-06-26T16:26:07Z",
    "updatedAt": "2026-06-26T16:26:07Z",
    "itemId": "5a9ed835b2b6a80133127c2f",
    "user": {
      "id": "69f549f8f8d01101ab6a643a",
      "ingameName": "105205",
      "slug": "105205",
      "avatar": "user/avatar/69f549f8f8d01101ab6a643a.c6578ed7.webp",
      "reputation": 3,
      "platform": "pc",
      "crossplay": true,
      "locale": "zh-hans",
      "status": "offline",
      "activity": {
        "type": "UNKNOWN",
        "details": "unknown"
      },
      "lastSeen": "2026-06-30T11:09:28Z"
    }
  },
  {
    "id": "6a3eb6f486fc399ad4a7c889",
    "type": "sell",
    "platinum": 20,
    "quantity": 2,
    "perTrade": 1,
    "visible": true,
    "createdAt": "2026-06-26T17:29:24Z",
    "updatedAt": "2026-06-26T17:29:24Z",
    "itemId": "5a9ed835b2b6a80133127c2f",
    "user": {
      "id": "6a18acd0abd3df000a79e088",
      "ingameName": "Billy296",
      "slug": "billy296",
      "reputation": 0,
      "platform": "pc",
      "crossplay": true,
      "locale": "zh-hans",
      "status": "offline",
      "activity": {
        "type": "UNKNOWN",
        "details": "unknown"
      },
      "lastSeen": "2026-06-30T18:40:07Z"
    }
  },
  {
    "id": "6a401f6086fc399ad4a9e224",
    "type": "sell",
    "platinum": 40,
    "quantity": 1,
    "perTrade": 1,
    "visible": true,
    "createdAt": "2026-06-27T19:07:12Z",
    "updatedAt": "2026-06-28T10:17:13Z",
    "itemId": "5a9ed835b2b6a80133127c2f",
    "user": {
      "id": "62848a705658b3020ceaa8ba",
      "ingameName": "Xangia",
      "slug": "xangia",
      "reputation": 25,
      "platform": "pc",
      "crossplay": true,
      "locale": "en",
      "status": "offline",
      "activity": {
        "type": "UNKNOWN",
        "details": "unknown"
      },
      "lastSeen": "2026-06-30T21:29:37Z"
    }
  },
  {
    "id": "6a4252de86fc399ad4acba4d",
    "type": "sell",
    "platinum": 20,
    "quantity": 1,
    "perTrade": 1,
    "visible": true,
    "createdAt": "2026-06-29T11:11:26Z",
    "updatedAt": "2026-06-29T11:11:26Z",
    "itemId": "5a9ed835b2b6a80133127c2f",
    "user": {
      "id": "6a166169310c5e017eff60be",
      "ingameName": "langoucolo",
      "slug": "langoucolo",
      "reputation": 0,
      "platform": "pc",
      "crossplay": true,
      "locale": "zh-hans",
      "status": "offline",
      "activity": {
        "type": "UNKNOWN",
        "details": "unknown"
      },
      "lastSeen": "2026-06-30T11:34:44Z"
    }
  },
  {
    "id": "6a42be0786fc399ad4ad3700",
    "type": "sell",
    "platinum": 25,
    "quantity": 1,
    "perTrade": 1,
    "visible": true,
    "createdAt": "2026-06-29T18:48:39Z",
    "updatedAt": "2026-06-29T18:48:39Z",
    "itemId": "5a9ed835b2b6a80133127c2f",
    "user": {
      "id": "65154ae7093f130199a935b9",
      "ingameName": "Sbirriot",
      "slug": "sbirriot",
      "reputation": 97,
      "platform": "pc",
      "crossplay": true,
      "locale": "ru",
      "status": "offline",
      "activity": {
        "type": "UNKNOWN",
        "details": "unknown"
      },
      "lastSeen": "2026-06-30T21:37:33Z"
    }
  },
  {
    "id": "6a42d85786fc399ad4ad57e5",
    "type": "sell",
    "platinum": 60,
    "quantity": 2,
    "perTrade": 1,
    "visible": true,
    "createdAt": "2026-06-29T20:40:55Z",
    "updatedAt": "2026-06-29T20:40:55Z",
    "itemId": "5a9ed835b2b6a80133127c2f",
    "user": {
      "id": "66e028f8adc83a2f788630a7",
      "ingameName": "Diego_Maelz",
      "slug": "diego-maelz",
      "avatar": "user/avatar/66e028f8adc83a2f788630a7.png?3ea5015127df72638e609b416e5e1a85",
      "reputation": 92,
      "platform": "pc",
      "crossplay": true,
      "locale": "ru",
      "status": "offline",
      "activity": {
        "type": "UNKNOWN",
        "details": "unknown"
      },
      "lastSeen": "2026-06-30T10:52:11Z"
    }
  },
  {
    "id": "6a4324112202c9dc0ad13008",
    "type": "sell",
    "platinum": 23,
    "quantity": 1,
    "perTrade": 1,
    "visible": true,
    "createdAt": "2026-06-30T02:04:01Z",
    "updatedAt": "2026-06-30T02:04:01Z",
    "itemId": "5a9ed835b2b6a80133127c2f",
    "user": {
      "id": "64969c816c031421ce0d09f1",
      "ingameName": "Forever-007",
      "slug": "forever-007",
      "reputation": 9,
      "platform": "pc",
      "crossplay": true,
      "locale": "zh-hans",
      "status": "offline",
      "activity": {
        "type": "UNKNOWN",
        "details": "unknown"
      },
      "lastSeen": "2026-06-30T15:45:55Z"
    }
  },
  {
    "id": "6a44150086fc399ad4aed2a2",
    "type": "sell",
    "platinum": 25,
    "quantity": 10,
    "perTrade": 1,
    "visible": true,
    "createdAt": "2026-06-30T19:12:00Z",
    "updatedAt": "2026-06-30T19:12:00Z",
    "itemId": "5a9ed835b2b6a80133127c2f",
    "user": {
      "id": "63af1c158f2b270c8c822ba9",
      "ingameName": "laid.over.1",
      "slug": "laid-over-1",
      "reputation": 2,
      "platform": "pc",
      "crossplay": true,
      "locale": "en",
      "status": "ingame",
      "activity": {
        "type": "UNKNOWN",
        "details": "unknown"
      },
      "lastSeen": "2026-06-30T21:24:18Z"
    }
  },
  {
    "id": "6a4439b02202c9dc0ad28b73",
    "type": "sell",
    "platinum": 20,
    "quantity": 1,
    "perTrade": 1,
    "visible": true,
    "createdAt": "2026-06-30T21:48:32Z",
    "updatedAt": "2026-06-30T21:48:32Z",
    "itemId": "5a9ed835b2b6a80133127c2f",
    "user": {
      "id": "6555e6660549dc0e4d25bf02",
      "ingameName": "Igams",
      "slug": "igams",
      "reputation": 6,
      "platform": "pc",
      "crossplay": true,
      "locale": "en",
      "status": "offline",
      "activity": {
        "type": "UNKNOWN",
        "details": "unknown"
      },
      "lastSeen": "2026-06-30T21:43:16Z"
    }
  }
]